{
  "cache_key": "c6b18d574f88246fc6b5d06e78cada7b",
  "model": "rerank-v3.5",
  "timestamp": "2026-02-15T02:46:23.354569+00:00",
  "query": "What is the address of ASX:PKO?",
  "top_n": 5,
  "response": [
    {
      "chunk_id": "E_2_183",
      "relevance_score": 0.89501935
    },
    {
      "chunk_id": "E_2_0",
      "relevance_score": 0.8808076
    },
    {
      "chunk_id": "E_2_2",
      "relevance_score": 0.68344116
    },
    {
      "chunk_id": "E_2_1",
      "relevance_score": 0.5553635
    },
    {
      "chunk_id": "E_2_3",
      "relevance_score": 0.528899
    }
  ]
}